tichr/PRC_ROC.py
tichr/RPmodel.py
tichr/RPpredictDEG.py
tichr/__init__.py
tichr/__main__.py
tichr/context.py
tichr/dumphic.py
tichr/highOrderStructure.py
tichr/insilico.py
tichr/large.py
tichr/multiEpiPredict.py
tichr/preprocess_hic.py
tichr/siteToGene.py
tichr/studyDEG.py
tichr/tichr.py
tichr/tichr_function.py
tichr/timeSeries.py
tichr/treatment.py
tichr/wasted.py
tichr/bashcode/ABC_make_candidate.sh
tichr/bashcode/bedClip
tichr/bashcode/bedGraphToBigWig
tichr/bashcode/bigWigAverageOverBed
tichr/bashcode/bigWigSummary
tichr/bashcode/coverageBed-tichr.sh
tichr/bashcode/coverageBed_bedGraph.sh
tichr/bashcode/coverageTSS.sh
tichr/bashcode/makeMatrixIntra.sh
tichr/bashcode/makeSurrondingBin.sh
tichr/bashcode/preprocessRP.sh
tichr/bashcode/processcoverage.sh
tichr/supportcode/EnhancersQNormRef.K562.txt.gz
tichr/supportcode/classheat.py
tichr/supportcode/overlap_predict_true.py
tichr/supportcode/overlap_predict_true.sh
tichr-0.1.7.dist-info/licenses/LICENSE
tichr-0.1.7.dist-info/METADATA
tichr-0.1.7.dist-info/WHEEL
tichr-0.1.7.dist-info/entry_points.txt
tichr-0.1.7.dist-info/top_level.txt
tichr-0.1.7.dist-info/RECORD
