Metadata-Version: 2.4
Name: tichr
Version: 0.1.7
Summary: TICHR: A computational tool designed to investigate transcriptional regulation
Author: Jiankang Wang
Author-email: wangjk321@gmail.com
Classifier: Programming Language :: Python :: 3
Classifier: License :: OSI Approved :: GNU General Public License v3 (GPLv3)
Classifier: Operating System :: OS Independent
Requires-Python: >=3.6
License-File: LICENSE
Requires-Dist: numpy
Requires-Dist: pandas
Requires-Dist: scipy
Requires-Dist: matplotlib
Requires-Dist: seaborn
Requires-Dist: pyBigWig
Requires-Dist: scikit-learn
Requires-Dist: hic-straw
Requires-Dist: statsmodels
Requires-Dist: pyranges
Requires-Dist: tqdm
Requires-Dist: rpy2
Requires-Dist: adjustText
Requires-Dist: umap-learn
Dynamic: author
Dynamic: author-email
Dynamic: classifier
Dynamic: license-file
Dynamic: requires-dist
Dynamic: requires-python
Dynamic: summary
